hydra_plugins/flyte_launcher_plugin/__init__.py
hydra_plugins/flyte_launcher_plugin/_flyte_ignore.py
hydra_plugins/flyte_launcher_plugin/_flyte_launcher.py
hydra_plugins/scaffold_searchpath_plugin/__init__.py
hydra_plugins/scaffold_searchpath_plugin/scaffold_searchpath_plugin.py
scaffold/__init__.py
scaffold/conf/__init__.py
scaffold/conf/scaffold/__init__.py
scaffold/conf/scaffold/artifact_manager.py
scaffold/conf/scaffold/ctx_manager.py
scaffold/conf/scaffold/entrypoint/__init__.py
scaffold/conf/scaffold/entrypoint/hydra_defaults.yaml
scaffold/conf/scaffold/entrypoint/logging/default.yaml
scaffold/conf/scaffold/entrypoint/logging/disabled.yaml
scaffold/conf/scaffold/entrypoint/logging/none.yaml
scaffold/conf/scaffold/entrypoint/logging/stdout.yaml
scaffold/conf/scaffold/entrypoint/logging/stdout_and_logfile.yaml
scaffold/conf/scaffold/flyte_launcher.py
scaffold/conf/scaffold/lightning/callbacks.py
scaffold/constants.py
scaffold/ctx_manager.py
scaffold/data/__init__.py
scaffold/data/artifact_manager/__init__.py
scaffold/data/artifact_manager/artifact_id_manager.py
scaffold/data/artifact_manager/artifact_logger.py
scaffold/data/artifact_manager/base.py
scaffold/data/artifact_manager/filesystem.py
scaffold/data/artifact_manager/wandb.py
scaffold/data/constants.py
scaffold/data/fs.py
scaffold/data/iterstream/__init__.py
scaffold/data/iterstream/base.py
scaffold/data/iterstream/iterators.py
scaffold/data/iterstream/source.py
scaffold/entrypoints/__init__.py
scaffold/entrypoints/entrypoint.py
scaffold/flyte/__init__.py
scaffold/flyte/core.py
scaffold/flyte/flyte_utils.py
scaffold/flyte/git.py
scaffold/flyte/image_builder.py
scaffold/hydra/__init__.py
scaffold/hydra/compose.py
scaffold/hydra/config_helpers.py
scaffold/hydra/constants.py
scaffold/hydra/custom.py
scaffold/hydra/initialize.py
scaffold/integration_test/__init__.py
scaffold/integration_test/conftest.py
scaffold/integration_test/helpers.py
scaffold/integration_test/shared_fixtures.py
mxm_scaffold-0.18.4.dist-info/METADATA
mxm_scaffold-0.18.4.dist-info/WHEEL
mxm_scaffold-0.18.4.dist-info/RECORD
