Metadata-Version: 2.3
Name: mxm-scaffold
Version: 0.18.4
Summary: Client library Created by the Merantix Momentum AI Platform Team
License: MIT
Author: Merantix Momentum GmbH
Requires-Python: >=3.9.0,<3.13
Classifier: Development Status :: 5 - Production/Stable
Classifier: License :: OSI Approved :: Apache Software License
Classifier: License :: OSI Approved :: MIT License
Classifier: Programming Language :: Python :: 3
Classifier: Programming Language :: Python :: 3.9
Classifier: Programming Language :: Python :: 3.10
Classifier: Programming Language :: Python :: 3.11
Classifier: Programming Language :: Python :: 3.12
Classifier: Typing :: Typed
Provides-Extra: all
Provides-Extra: data
Provides-Extra: flyte
Provides-Extra: torch
Provides-Extra: wandb
Requires-Dist: PyJWT (>=2.4.0)
Requires-Dist: botocore (>=1.36.3)
Requires-Dist: cookiecutter (>=2.1.1,<3.0.0) ; extra == "flyte" or extra == "all"
Requires-Dist: docker (>=7.1.0,<8.0.0) ; extra == "flyte" or extra == "all"
Requires-Dist: flatten-dict
Requires-Dist: flytekit (>=1.14.3,<2.0.0) ; extra == "flyte" or extra == "all"
Requires-Dist: flytekitplugins-omegaconf ; extra == "flyte" or extra == "all"
Requires-Dist: flytekitplugins-pod ; extra == "flyte" or extra == "all"
Requires-Dist: fsspec (>=2024.12.0) ; extra == "data"
Requires-Dist: gcsfs (>=2024.12.0) ; extra == "data"
Requires-Dist: hydra-core (>=1.0.4,<2.0.0)
Requires-Dist: jsonpickle ; extra == "flyte" or extra == "all"
Requires-Dist: marshmallow-enum (>=1.5.1,<2.0.0) ; extra == "flyte" or extra == "all"
Requires-Dist: numpy (<2.0.0) ; python_version < "3.10"
Requires-Dist: numpy ; python_version >= "3.10" and python_version < "4.0"
Requires-Dist: psutil
Requires-Dist: pynvml
Requires-Dist: pyprojroot (>=0.3.0,<0.4.0) ; extra == "flyte" or extra == "all"
Requires-Dist: pytorch-lightning (>=1.9,<2.5) ; extra == "torch" or extra == "all"
Requires-Dist: random-name
Requires-Dist: torch (>=1.13.0) ; extra == "torch" or extra == "all"
Requires-Dist: tqdm
Requires-Dist: urllib3 (>=1.26.5)
Requires-Dist: wandb ; extra == "wandb" or extra == "all"
Project-URL: Documentation, https://docs.scaffold.merantix-momentum.cloud/
Project-URL: Homepage, https://merantix-momentum.com
Project-URL: Repository, https://github.com/merantix-momentum/scaffold-core/
